cartograph/__init__.py
cartograph/cartograph.py
cartograph/feature.py
cartograph/map.py
cartograph/projection.py
cartograph/style.py
cartograph-0.0.1.dist-info/LICENSE
cartograph-0.0.1.dist-info/METADATA
cartograph-0.0.1.dist-info/WHEEL
cartograph-0.0.1.dist-info/top_level.txt
cartograph-0.0.1.dist-info/RECORD
