Metadata-Version: 2.1
Name: cartograph
Version: 0.0.1
Summary: A package for drawing map tiles
Home-page: https://alastairflynn.com/cartograph
Author: Alastair Flynn
Author-email: contact@alastairflynn.com
License: UNKNOWN
Project-URL: Documentation, https://alastairflynn.com/cartograph
Project-URL: Source code, https://github.com/alastairflynn/cartograph
Platform: UNKNOWN
Classifier: Programming Language :: Python :: 3
Classifier: License :: OSI Approved :: MIT License
Classifier: Operating System :: OS Independent
Requires-Python: >=3.5
Requires-Dist: numpy (>=1.3.0)
Requires-Dist: scipy (>=0.9.0)
Requires-Dist: matplotlib (>=3.0.0)
